MSTeamsdataretrieval/TeamsDataRetrival.py
MSTeamsdataretrieval/__init__.py
tests/__init__.py
tests/test_Teamsdataretrieval.py
MSTeamsdataretrieval_neeti_sharma1-0.0.3.dist-info/LICENCE
MSTeamsdataretrieval_neeti_sharma1-0.0.3.dist-info/METADATA
MSTeamsdataretrieval_neeti_sharma1-0.0.3.dist-info/WHEEL
MSTeamsdataretrieval_neeti_sharma1-0.0.3.dist-info/top_level.txt
MSTeamsdataretrieval_neeti_sharma1-0.0.3.dist-info/RECORD
